README.md
libbrotlicommon.so
libbrotlidec.so
libfreetype.so
pylab.py
setup.py
matplotlib/__init__.py
matplotlib/__init__.pyi
matplotlib/_afm.py
matplotlib/_animation_data.py
matplotlib/_blocking_input.py
matplotlib/_c_internal_utils.cpython-312.so
matplotlib/_c_internal_utils.pyi
matplotlib/_cm.py
matplotlib/_cm_listed.py
matplotlib/_color_data.py
matplotlib/_color_data.pyi
matplotlib/_constrained_layout.py
matplotlib/_docstring.py
matplotlib/_docstring.pyi
matplotlib/_enums.py
matplotlib/_enums.pyi
matplotlib/_fontconfig_pattern.py
matplotlib/_image.cpython-312.so
matplotlib/_image.pyi
matplotlib/_internal_utils.py
matplotlib/_layoutgrid.py
matplotlib/_mathtext.py
matplotlib/_mathtext_data.py
matplotlib/_path.cpython-312.so
matplotlib/_path.pyi
matplotlib/_pylab_helpers.py
matplotlib/_pylab_helpers.pyi
matplotlib/_qhull.cpython-312.so
matplotlib/_qhull.pyi
matplotlib/_text_helpers.py
matplotlib/_tight_bbox.py
matplotlib/_tight_layout.py
matplotlib/_tri.cpython-312.so
matplotlib/_tri.pyi
matplotlib/_ttconv.cpython-312.so
matplotlib/_ttconv.pyi
matplotlib/_type1font.py
matplotlib/_version.py
matplotlib/animation.py
matplotlib/animation.pyi
matplotlib/artist.py
matplotlib/artist.pyi
matplotlib/axis.py
matplotlib/axis.pyi
matplotlib/backend_bases.py
matplotlib/backend_bases.pyi
matplotlib/backend_managers.py
matplotlib/backend_managers.pyi
matplotlib/backend_tools.py
matplotlib/backend_tools.pyi
matplotlib/bezier.py
matplotlib/bezier.pyi
matplotlib/category.py
matplotlib/cbook.py
matplotlib/cbook.pyi
matplotlib/cm.py
matplotlib/cm.pyi
matplotlib/collections.py
matplotlib/collections.pyi
matplotlib/colorbar.py
matplotlib/colorbar.pyi
matplotlib/colors.py
matplotlib/colors.pyi
matplotlib/container.py
matplotlib/container.pyi
matplotlib/contour.py
matplotlib/contour.pyi
matplotlib/dates.py
matplotlib/dviread.py
matplotlib/dviread.pyi
matplotlib/figure.py
matplotlib/figure.pyi
matplotlib/font_manager.py
matplotlib/font_manager.pyi
matplotlib/ft2font.cpython-312.so
matplotlib_aipy.egg-info/PKG-INFO
matplotlib_aipy.egg-info/SOURCES.txt
matplotlib_aipy.egg-info/dependency_links.txt
matplotlib_aipy.egg-info/requires.txt
matplotlib_aipy.egg-info/top_level.txt
