Metadata-Version: 2.4
Name: matplotlib-aipy
Version: 3.9.2
Summary: Matplotlib is a comprehensive library for creating static, animated, and interactive visualizations in Python.
Home-page: https://qpypi.qpython.org/project/matplotlib-aipy/
Author: The QPYPI Team
Author-email: qpypi@qpython.org
License: OSI Approved :: Python Software Foundation License
Classifier: Intended Audience :: Developers
Classifier: Intended Audience :: Education
Classifier: Intended Audience :: Information Technology
Classifier: Intended Audience :: End Users/Desktop
Classifier: License :: OSI Approved :: Apache Software License
Classifier: Operating System :: Android
Classifier: Programming Language :: Python
Classifier: Programming Language :: Python :: 3.12
Classifier: Topic :: Software Development
Requires-Dist: kiwisolver-qpython
Requires-Dist: numpy-aipy
Requires-Dist: pillow-qpython
Requires-Dist: pyparsing
Requires-Dist: backports.functools_lru_cache
Requires-Dist: cycler
Requires-Dist: python-dateutil
Dynamic: author
Dynamic: author-email
Dynamic: classifier
Dynamic: description
Dynamic: description-content-type
Dynamic: home-page
Dynamic: license
Dynamic: requires-dist
Dynamic: summary
